flash/__init__.py
flash/analysis.py
flash/preprocessing.py
flash/utils.py
flash_lib-0.1.1.dist-info/LICENSE
flash_lib-0.1.1.dist-info/METADATA
flash_lib-0.1.1.dist-info/WHEEL
flash_lib-0.1.1.dist-info/RECORD
